pyfost/adminui/__init__.py
pyfost/adminui/admin.py
pyfost/adminui/model_card.py
pyfost/adminui/model_view.py
pyfost/adminui/examples/backend_api.py
pyfost/adminui/examples/simple.py
pyfost/adminui/renderers/column.py
pyfost/adminui/renderers/field.py
pyfost/adminui/renderers/model.py
pyfost_adminui-0.1.4.dist-info/METADATA
pyfost_adminui-0.1.4.dist-info/WHEEL
pyfost_adminui-0.1.4.dist-info/licenses/LICENSE
pyfost_adminui-0.1.4.dist-info/RECORD
