Metadata-Version: 2.4
Name: pyfost.adminui
Version: 0.1.4
Summary: Admin / CRUD frontend for pyfost webapps
Project-URL: Documentation, https://github.com/fost-studio/pyfost.adminui#readme
Project-URL: Issues, https://github.com/fost-studio/pyfost.adminui/issues
Project-URL: Source, https://github.com/fost-studio/pyfost.adminui
Author-email: Dee <dee.somethech@gmail.com>
License-Expression: GPL-3.0-or-later
License-File: LICENSE
Classifier: Development Status :: 4 - Beta
Classifier: Programming Language :: Python
Classifier: Programming Language :: Python :: 3.12
Classifier: Programming Language :: Python :: Implementation :: CPython
Classifier: Programming Language :: Python :: Implementation :: PyPy
Requires-Python: >=3.12
Requires-Dist: nicegui
Requires-Dist: pydantic
